mn_squared/__init__.py
mn_squared/_jsd_distance.py
mn_squared/_validators.py
mn_squared/core.py
mn_squared/py.typed
mn_squared/types.py
mn_squared/cdf_backends/__init__.py
mn_squared/cdf_backends/base.py
mn_squared/cdf_backends/exact.py
mn_squared/cdf_backends/mc_multinomial.py
mn_squared/cdf_backends/mc_normal.py
mn_squared/null_structures/__init__.py
mn_squared/null_structures/indexed_hypotheses.py
mn_squared/null_structures/null_hypothesis.py
mn_squared-1.0.0.dist-info/licenses/LICENSE
mn_squared-1.0.0.dist-info/METADATA
mn_squared-1.0.0.dist-info/WHEEL
mn_squared-1.0.0.dist-info/top_level.txt
mn_squared-1.0.0.dist-info/RECORD
