Metadata-Version: 2.4
Name: mn-squared
Version: 1.0.0
Summary: Multi-Null Non-Parametric (MN-squared) Jensen–Shannon Distance (JSd) hypothesis test.
Author-email: ALGES <contacto@alges.cl>
License: Apache License
Keywords: statistics,hypothesis-testing,multinomial,Jensen-Shannon,information-theory
Classifier: Programming Language :: Python :: 3
Classifier: Programming Language :: Python :: 3 :: Only
Classifier: Operating System :: OS Independent
Classifier: Typing :: Typed
Requires-Python: >=3.12
License-File: LICENSE
Requires-Dist: numpy>=1.24
Provides-Extra: dev
Requires-Dist: pytest>=7.4; extra == "dev"
Requires-Dist: pytest-cov>=4.1; extra == "dev"
Requires-Dist: hypothesis>=6.88; extra == "dev"
Requires-Dist: mypy>=1.5; extra == "dev"
Requires-Dist: ruff>=0.4; extra == "dev"
Requires-Dist: pre-commit>=3.6; extra == "dev"
Provides-Extra: docs
Requires-Dist: sphinx>=7.2; extra == "docs"
Requires-Dist: furo>=2024.1.29; extra == "docs"
Requires-Dist: myst-parser>=2.0; extra == "docs"
Requires-Dist: sphinx-autodoc-typehints>=2.0; extra == "docs"
Requires-Dist: sphinx-copybutton>=0.5.2; extra == "docs"
Provides-Extra: demo
Requires-Dist: notebook>=7.0.0; extra == "demo"
Requires-Dist: jupyter>=1.0.0; extra == "demo"
Requires-Dist: matplotlib>=3.10; extra == "demo"
Provides-Extra: exp
Requires-Dist: pandas>=2.3; extra == "exp"
Requires-Dist: scipy>=1.16; extra == "exp"
Requires-Dist: hyppo>=0.5.2; extra == "exp"
Requires-Dist: rpy2>=3.6; extra == "exp"
Requires-Dist: tqdm>=4.67; extra == "exp"
Requires-Dist: numpy<2.4; extra == "exp"
Dynamic: license-file
